annoy-stubs/METADATA.toml
annoy-stubs/__init__.pyi
annoy-stubs/annoylib.pyi
types_annoy-1.17.8.3.dist-info/METADATA
types_annoy-1.17.8.3.dist-info/WHEEL
types_annoy-1.17.8.3.dist-info/top_level.txt
types_annoy-1.17.8.3.dist-info/RECORD
